kognie_api/__init__.py
kognie_api/main.py
kognie_api-1.4.0.dist-info/METADATA
kognie_api-1.4.0.dist-info/WHEEL
kognie_api-1.4.0.dist-info/top_level.txt
kognie_api-1.4.0.dist-info/RECORD
