Metadata-Version: 2.1
Name: kognie-api
Version: 1.4.0
Author: Kognie
Requires-Dist: setuptools>=65.5.0
Requires-Dist: requests>=2.32.3
